pybinbot/__init__.py
pybinbot/py.typed
pybinbot/apis/binance/base.py
pybinbot/apis/binance/exceptions.py
pybinbot/apis/binbot/base.py
pybinbot/apis/binbot/exceptions.py
pybinbot/apis/kucoin/base.py
pybinbot/apis/kucoin/exceptions.py
pybinbot/apis/kucoin/market.py
pybinbot/apis/kucoin/orders.py
pybinbot/apis/kucoin/rest.py
pybinbot/models/__init__.py
pybinbot/models/bot_base.py
pybinbot/models/deal.py
pybinbot/models/order.py
pybinbot/models/routes.py
pybinbot/models/signals.py
pybinbot/shared/__init__.py
pybinbot/shared/cache.py
pybinbot/shared/enums.py
pybinbot/shared/handlers.py
pybinbot/shared/heikin_ashi.py
pybinbot/shared/indicators.py
pybinbot/shared/logging_config.py
pybinbot/shared/maths.py
pybinbot/shared/timestamps.py
pybinbot/shared/types.py
pybinbot/streaming/async_producer.py
pybinbot/streaming/binance/async_socket_client.py
pybinbot/streaming/binance/socket_client.py
pybinbot/streaming/binance/socket_manager.py
pybinbot/streaming/kucoin/kucoin_async_client.py
pybinbot-0.4.39.dist-info/licenses/LICENSE
pybinbot-0.4.39.dist-info/METADATA
pybinbot-0.4.39.dist-info/WHEEL
pybinbot-0.4.39.dist-info/top_level.txt
pybinbot-0.4.39.dist-info/RECORD
