Metadata-Version: 2.4
Name: pybinbot
Version: 0.4.39
Summary: Utility functions for the binbot project.
Author-email: Carlos Wu <carkodw@gmail.com>
Requires-Python: >=3.11
License-File: LICENSE
Requires-Dist: pydantic[email]>=2.0.0
Requires-Dist: numpy==2.2.0
Requires-Dist: pandas>=2.2.3
Requires-Dist: pymongo==4.6.3
Requires-Dist: pandas-stubs>=2.3.3.251219
Requires-Dist: requests>=2.32.5
Requires-Dist: kucoin-universal-sdk>=1.3.0
Requires-Dist: aiohttp>=3.13.3
Requires-Dist: python-dotenv>=1.2.1
Requires-Dist: aiokafka>=0.13.0
Provides-Extra: dev
Requires-Dist: pytest>=9.0.2; extra == "dev"
Requires-Dist: ruff>=0.11.12; extra == "dev"
Requires-Dist: mypy>=1.19.1; extra == "dev"
Requires-Dist: types-requests>=2.32.4.20260107; extra == "dev"
Requires-Dist: httpx>=0.28.1; extra == "dev"
Requires-Dist: pytest-asyncio>=1.3.0; extra == "dev"
Dynamic: license-file
